{"nodes": [{"id": "upload_module", "label": "upload.module.ts", "file_type": "code", "source_file": "apps\\api\\src\\modules\\upload\\upload.module.ts", "source_location": "L1"}, {"id": "upload_module_uploadmodule", "label": "UploadModule", "file_type": "code", "source_file": "apps\\api\\src\\modules\\upload\\upload.module.ts", "source_location": "L13"}], "edges": [{"source": "upload_module", "target": "common", "relation": "imports_from", "confidence": "EXTRACTED", "source_file": "apps\\api\\src\\modules\\upload\\upload.module.ts", "source_location": "L1", "weight": 1.0}, {"source": "upload_module", "target": "typeorm", "relation": "imports_from", "confidence": "EXTRACTED", "source_file": "apps\\api\\src\\modules\\upload\\upload.module.ts", "source_location": "L2", "weight": 1.0}, {"source": "upload_module", "target": "entities", "relation": "imports_from", "confidence": "EXTRACTED", "source_file": "apps\\api\\src\\modules\\upload\\upload.module.ts", "source_location": "L3", "weight": 1.0}, {"source": "upload_module", "target": "upload_service", "relation": "imports_from", "confidence": "EXTRACTED", "source_file": "apps\\api\\src\\modules\\upload\\upload.module.ts", "source_location": "L4", "weight": 1.0}, {"source": "upload_module", "target": "upload_controller", "relation": "imports_from", "confidence": "EXTRACTED", "source_file": "apps\\api\\src\\modules\\upload\\upload.module.ts", "source_location": "L5", "weight": 1.0}, {"source": "upload_module", "target": "upload_module_uploadmodule", "relation": "contains", "confidence": "EXTRACTED", "source_file": "apps\\api\\src\\modules\\upload\\upload.module.ts", "source_location": "L13", "weight": 1.0}]}