{"nodes": [{"id": "super_admin_controller", "label": "super-admin.controller.ts", "file_type": "code", "source_file": "apps\\api\\src\\modules\\super-admin\\super-admin.controller.ts", "source_location": "L1"}, {"id": "super_admin_controller_superadmincontroller", "label": "SuperAdminController", "file_type": "code", "source_file": "apps\\api\\src\\modules\\super-admin\\super-admin.controller.ts", "source_location": "L25"}, {"id": "super_admin_controller_superadmincontroller_constructor", "label": ".constructor()", "file_type": "code", "source_file": "apps\\api\\src\\modules\\super-admin\\super-admin.controller.ts", "source_location": "L26"}, {"id": "super_admin_controller_superadmincontroller_getdashboard", "label": ".getDashboard()", "file_type": "code", "source_file": "apps\\api\\src\\modules\\super-admin\\super-admin.controller.ts", "source_location": "L31"}, {"id": "super_admin_controller_superadmincontroller_listclients", "label": ".listClients()", "file_type": "code", "source_file": "apps\\api\\src\\modules\\super-admin\\super-admin.controller.ts", "source_location": "L38"}, {"id": "super_admin_controller_superadmincontroller_getclient", "label": ".getClient()", "file_type": "code", "source_file": "apps\\api\\src\\modules\\super-admin\\super-admin.controller.ts", "source_location": "L43"}, {"id": "super_admin_controller_superadmincontroller_createclient", "label": ".createClient()", "file_type": "code", "source_file": "apps\\api\\src\\modules\\super-admin\\super-admin.controller.ts", "source_location": "L48"}, {"id": "super_admin_controller_superadmincontroller_updateclient", "label": ".updateClient()", "file_type": "code", "source_file": "apps\\api\\src\\modules\\super-admin\\super-admin.controller.ts", "source_location": "L56"}, {"id": "super_admin_controller_superadmincontroller_deleteclient", "label": ".deleteClient()", "file_type": "code", "source_file": "apps\\api\\src\\modules\\super-admin\\super-admin.controller.ts", "source_location": "L66"}, {"id": "super_admin_controller_superadmincontroller_checkconnection", "label": ".checkConnection()", "file_type": "code", "source_file": "apps\\api\\src\\modules\\super-admin\\super-admin.controller.ts", "source_location": "L76"}, {"id": "super_admin_controller_superadmincontroller_toggleoverride", "label": ".toggleOverride()", "file_type": "code", "source_file": "apps\\api\\src\\modules\\super-admin\\super-admin.controller.ts", "source_location": "L81"}, {"id": "super_admin_controller_superadmincontroller_manualactivate", "label": ".manualActivate()", "file_type": "code", "source_file": "apps\\api\\src\\modules\\super-admin\\super-admin.controller.ts", "source_location": "L89"}, {"id": "super_admin_controller_superadmincontroller_extendsubscription", "label": ".extendSubscription()", "file_type": "code", "source_file": "apps\\api\\src\\modules\\super-admin\\super-admin.controller.ts", "source_location": "L98"}, {"id": "super_admin_controller_superadmincontroller_getlicensekeys", "label": ".getLicenseKeys()", "file_type": "code", "source_file": "apps\\api\\src\\modules\\super-admin\\super-admin.controller.ts", "source_location": "L109"}, {"id": "super_admin_controller_superadmincontroller_generatelicensekey", "label": ".generateLicenseKey()", "file_type": "code", "source_file": "apps\\api\\src\\modules\\super-admin\\super-admin.controller.ts", "source_location": "L114"}, {"id": "super_admin_controller_superadmincontroller_revokelicensekey", "label": ".revokeLicenseKey()", "file_type": "code", "source_file": "apps\\api\\src\\modules\\super-admin\\super-admin.controller.ts", "source_location": "L123"}, {"id": "super_admin_controller_superadmincontroller_regeneratelicensekey", "label": ".regenerateLicenseKey()", "file_type": "code", "source_file": "apps\\api\\src\\modules\\super-admin\\super-admin.controller.ts", "source_location": "L132"}, {"id": "super_admin_controller_superadmincontroller_listplans", "label": ".listPlans()", "file_type": "code", "source_file": "apps\\api\\src\\modules\\super-admin\\super-admin.controller.ts", "source_location": "L143"}, {"id": "super_admin_controller_superadmincontroller_getplanstats", "label": ".getPlanStats()", "file_type": "code", "source_file": "apps\\api\\src\\modules\\super-admin\\super-admin.controller.ts", "source_location": "L148"}, {"id": "super_admin_controller_superadmincontroller_getplan", "label": ".getPlan()", "file_type": "code", "source_file": "apps\\api\\src\\modules\\super-admin\\super-admin.controller.ts", "source_location": "L153"}, {"id": "super_admin_controller_superadmincontroller_createplan", "label": ".createPlan()", "file_type": "code", "source_file": "apps\\api\\src\\modules\\super-admin\\super-admin.controller.ts", "source_location": "L158"}, {"id": "super_admin_controller_superadmincontroller_updateplan", "label": ".updatePlan()", "file_type": "code", "source_file": "apps\\api\\src\\modules\\super-admin\\super-admin.controller.ts", "source_location": "L166"}, {"id": "super_admin_controller_superadmincontroller_deleteplan", "label": ".deletePlan()", "file_type": "code", "source_file": "apps\\api\\src\\modules\\super-admin\\super-admin.controller.ts", "source_location": "L176"}], "edges": [{"source": "super_admin_controller", "target": "common", "relation": "imports_from", "confidence": "EXTRACTED", "source_file": "apps\\api\\src\\modules\\super-admin\\super-admin.controller.ts", "source_location": "L1", "weight": 1.0}, {"source": "super_admin_controller", "target": "super_admin_service", "relation": "imports_from", "confidence": "EXTRACTED", "source_file": "apps\\api\\src\\modules\\super-admin\\super-admin.controller.ts", "source_location": "L15", "weight": 1.0}, {"source": "super_admin_controller", "target": "dto", "relation": "imports_from", "confidence": "EXTRACTED", "source_file": "apps\\api\\src\\modules\\super-admin\\super-admin.controller.ts", "source_location": "L16", "weight": 1.0}, {"source": "super_admin_controller", "target": "guards", "relation": "imports_from", "confidence": "EXTRACTED", "source_file": "apps\\api\\src\\modules\\super-admin\\super-admin.controller.ts", "source_location": "L17", "weight": 1.0}, {"source": "super_admin_controller", "target": "roles_decorator", "relation": "imports_from", "confidence": "EXTRACTED", "source_file": "apps\\api\\src\\modules\\super-admin\\super-admin.controller.ts", "source_location": "L18", "weight": 1.0}, {"source": "super_admin_controller", "target": "decorators", "relation": "imports_from", "confidence": "EXTRACTED", "source_file": "apps\\api\\src\\modules\\super-admin\\super-admin.controller.ts", "source_location": "L19", "weight": 1.0}, {"source": "super_admin_controller", "target": "shared", "relation": "imports_from", "confidence": "EXTRACTED", "source_file": "apps\\api\\src\\modules\\super-admin\\super-admin.controller.ts", "source_location": "L20", "weight": 1.0}, {"source": "super_admin_controller", "target": "super_admin_controller_superadmincontroller", "relation": "contains", "confidence": "EXTRACTED", "source_file": "apps\\api\\src\\modules\\super-admin\\super-admin.controller.ts", "source_location": "L25", "weight": 1.0}, {"source": "super_admin_controller_superadmincontroller", "target": "super_admin_controller_superadmincontroller_constructor", "relation": "method", "confidence": "EXTRACTED", "source_file": "apps\\api\\src\\modules\\super-admin\\super-admin.controller.ts", "source_location": "L26", "weight": 1.0}, {"source": "super_admin_controller_superadmincontroller", "target": "super_admin_controller_superadmincontroller_getdashboard", "relation": "method", "confidence": "EXTRACTED", "source_file": "apps\\api\\src\\modules\\super-admin\\super-admin.controller.ts", "source_location": "L31", "weight": 1.0}, {"source": "super_admin_controller_superadmincontroller", "target": "super_admin_controller_superadmincontroller_listclients", "relation": "method", "confidence": "EXTRACTED", "source_file": "apps\\api\\src\\modules\\super-admin\\super-admin.controller.ts", "source_location": "L38", "weight": 1.0}, {"source": "super_admin_controller_superadmincontroller", "target": "super_admin_controller_superadmincontroller_getclient", "relation": "method", "confidence": "EXTRACTED", "source_file": "apps\\api\\src\\modules\\super-admin\\super-admin.controller.ts", "source_location": "L43", "weight": 1.0}, {"source": "super_admin_controller_superadmincontroller", "target": "super_admin_controller_superadmincontroller_createclient", "relation": "method", "confidence": "EXTRACTED", "source_file": "apps\\api\\src\\modules\\super-admin\\super-admin.controller.ts", "source_location": "L48", "weight": 1.0}, {"source": "super_admin_controller_superadmincontroller", "target": "super_admin_controller_superadmincontroller_updateclient", "relation": "method", "confidence": "EXTRACTED", "source_file": "apps\\api\\src\\modules\\super-admin\\super-admin.controller.ts", "source_location": "L56", "weight": 1.0}, {"source": "super_admin_controller_superadmincontroller", "target": "super_admin_controller_superadmincontroller_deleteclient", "relation": "method", "confidence": "EXTRACTED", "source_file": "apps\\api\\src\\modules\\super-admin\\super-admin.controller.ts", "source_location": "L66", "weight": 1.0}, {"source": "super_admin_controller_superadmincontroller", "target": "super_admin_controller_superadmincontroller_checkconnection", "relation": "method", "confidence": "EXTRACTED", "source_file": "apps\\api\\src\\modules\\super-admin\\super-admin.controller.ts", "source_location": "L76", "weight": 1.0}, {"source": "super_admin_controller_superadmincontroller", "target": "super_admin_controller_superadmincontroller_toggleoverride", "relation": "method", "confidence": "EXTRACTED", "source_file": "apps\\api\\src\\modules\\super-admin\\super-admin.controller.ts", "source_location": "L81", "weight": 1.0}, {"source": "super_admin_controller_superadmincontroller", "target": "super_admin_controller_superadmincontroller_manualactivate", "relation": "method", "confidence": "EXTRACTED", "source_file": "apps\\api\\src\\modules\\super-admin\\super-admin.controller.ts", "source_location": "L89", "weight": 1.0}, {"source": "super_admin_controller_superadmincontroller", "target": "super_admin_controller_superadmincontroller_extendsubscription", "relation": "method", "confidence": "EXTRACTED", "source_file": "apps\\api\\src\\modules\\super-admin\\super-admin.controller.ts", "source_location": "L98", "weight": 1.0}, {"source": "super_admin_controller_superadmincontroller", "target": "super_admin_controller_superadmincontroller_getlicensekeys", "relation": "method", "confidence": "EXTRACTED", "source_file": "apps\\api\\src\\modules\\super-admin\\super-admin.controller.ts", "source_location": "L109", "weight": 1.0}, {"source": "super_admin_controller_superadmincontroller", "target": "super_admin_controller_superadmincontroller_generatelicensekey", "relation": "method", "confidence": "EXTRACTED", "source_file": "apps\\api\\src\\modules\\super-admin\\super-admin.controller.ts", "source_location": "L114", "weight": 1.0}, {"source": "super_admin_controller_superadmincontroller", "target": "super_admin_controller_superadmincontroller_revokelicensekey", "relation": "method", "confidence": "EXTRACTED", "source_file": "apps\\api\\src\\modules\\super-admin\\super-admin.controller.ts", "source_location": "L123", "weight": 1.0}, {"source": "super_admin_controller_superadmincontroller", "target": "super_admin_controller_superadmincontroller_regeneratelicensekey", "relation": "method", "confidence": "EXTRACTED", "source_file": "apps\\api\\src\\modules\\super-admin\\super-admin.controller.ts", "source_location": "L132", "weight": 1.0}, {"source": "super_admin_controller_superadmincontroller", "target": "super_admin_controller_superadmincontroller_listplans", "relation": "method", "confidence": "EXTRACTED", "source_file": "apps\\api\\src\\modules\\super-admin\\super-admin.controller.ts", "source_location": "L143", "weight": 1.0}, {"source": "super_admin_controller_superadmincontroller", "target": "super_admin_controller_superadmincontroller_getplanstats", "relation": "method", "confidence": "EXTRACTED", "source_file": "apps\\api\\src\\modules\\super-admin\\super-admin.controller.ts", "source_location": "L148", "weight": 1.0}, {"source": "super_admin_controller_superadmincontroller", "target": "super_admin_controller_superadmincontroller_getplan", "relation": "method", "confidence": "EXTRACTED", "source_file": "apps\\api\\src\\modules\\super-admin\\super-admin.controller.ts", "source_location": "L153", "weight": 1.0}, {"source": "super_admin_controller_superadmincontroller", "target": "super_admin_controller_superadmincontroller_createplan", "relation": "method", "confidence": "EXTRACTED", "source_file": "apps\\api\\src\\modules\\super-admin\\super-admin.controller.ts", "source_location": "L158", "weight": 1.0}, {"source": "super_admin_controller_superadmincontroller", "target": "super_admin_controller_superadmincontroller_updateplan", "relation": "method", "confidence": "EXTRACTED", "source_file": "apps\\api\\src\\modules\\super-admin\\super-admin.controller.ts", "source_location": "L166", "weight": 1.0}, {"source": "super_admin_controller_superadmincontroller", "target": "super_admin_controller_superadmincontroller_deleteplan", "relation": "method", "confidence": "EXTRACTED", "source_file": "apps\\api\\src\\modules\\super-admin\\super-admin.controller.ts", "source_location": "L176", "weight": 1.0}]}