{"nodes": [{"id": "property_search_service", "label": "property-search.service.ts", "file_type": "code", "source_file": "apps\\api\\src\\modules\\property\\property-search.service.ts", "source_location": "L1"}, {"id": "property_search_service_propertysearchservice", "label": "PropertySearchService", "file_type": "code", "source_file": "apps\\api\\src\\modules\\property\\property-search.service.ts", "source_location": "L13"}, {"id": "property_search_service_propertysearchservice_constructor", "label": ".constructor()", "file_type": "code", "source_file": "apps\\api\\src\\modules\\property\\property-search.service.ts", "source_location": "L14"}, {"id": "property_search_service_propertysearchservice_search", "label": ".search()", "file_type": "code", "source_file": "apps\\api\\src\\modules\\property\\property-search.service.ts", "source_location": "L19"}, {"id": "property_search_service_propertysearchservice_applyfilters", "label": ".applyFilters()", "file_type": "code", "source_file": "apps\\api\\src\\modules\\property\\property-search.service.ts", "source_location": "L40"}, {"id": "property_search_service_propertysearchservice_applysorting", "label": ".applySorting()", "file_type": "code", "source_file": "apps\\api\\src\\modules\\property\\property-search.service.ts", "source_location": "L59"}], "edges": [{"source": "property_search_service", "target": "common", "relation": "imports_from", "confidence": "EXTRACTED", "source_file": "apps\\api\\src\\modules\\property\\property-search.service.ts", "source_location": "L1", "weight": 1.0}, {"source": "property_search_service", "target": "typeorm", "relation": "imports_from", "confidence": "EXTRACTED", "source_file": "apps\\api\\src\\modules\\property\\property-search.service.ts", "source_location": "L2", "weight": 1.0}, {"source": "property_search_service", "target": "typeorm", "relation": "imports_from", "confidence": "EXTRACTED", "source_file": "apps\\api\\src\\modules\\property\\property-search.service.ts", "source_location": "L3", "weight": 1.0}, {"source": "property_search_service", "target": "entities", "relation": "imports_from", "confidence": "EXTRACTED", "source_file": "apps\\api\\src\\modules\\property\\property-search.service.ts", "source_location": "L4", "weight": 1.0}, {"source": "property_search_service", "target": "dto", "relation": "imports_from", "confidence": "EXTRACTED", "source_file": "apps\\api\\src\\modules\\property\\property-search.service.ts", "source_location": "L5", "weight": 1.0}, {"source": "property_search_service", "target": "property_search_service_propertysearchservice", "relation": "contains", "confidence": "EXTRACTED", "source_file": "apps\\api\\src\\modules\\property\\property-search.service.ts", "source_location": "L13", "weight": 1.0}, {"source": "property_search_service_propertysearchservice", "target": "property_search_service_propertysearchservice_constructor", "relation": "method", "confidence": "EXTRACTED", "source_file": "apps\\api\\src\\modules\\property\\property-search.service.ts", "source_location": "L14", "weight": 1.0}, {"source": "property_search_service_propertysearchservice", "target": "property_search_service_propertysearchservice_search", "relation": "method", "confidence": "EXTRACTED", "source_file": "apps\\api\\src\\modules\\property\\property-search.service.ts", "source_location": "L19", "weight": 1.0}, {"source": "property_search_service_propertysearchservice", "target": "property_search_service_propertysearchservice_applyfilters", "relation": "method", "confidence": "EXTRACTED", "source_file": "apps\\api\\src\\modules\\property\\property-search.service.ts", "source_location": "L40", "weight": 1.0}, {"source": "property_search_service_propertysearchservice", "target": "property_search_service_propertysearchservice_applysorting", "relation": "method", "confidence": "EXTRACTED", "source_file": "apps\\api\\src\\modules\\property\\property-search.service.ts", "source_location": "L59", "weight": 1.0}, {"source": "property_search_service_propertysearchservice_search", "target": "property_search_service_propertysearchservice_applyfilters", "relation": "calls", "confidence": "EXTRACTED", "source_file": "apps\\api\\src\\modules\\property\\property-search.service.ts", "source_location": "L28", "weight": 1.0}, {"source": "property_search_service_propertysearchservice_search", "target": "property_search_service_propertysearchservice_applysorting", "relation": "calls", "confidence": "EXTRACTED", "source_file": "apps\\api\\src\\modules\\property\\property-search.service.ts", "source_location": "L29", "weight": 1.0}]}