{"nodes": [{"id": "1712520000000_feedimport", "label": "1712520000000-FeedImport.ts", "file_type": "code", "source_file": "apps\\api\\src\\database\\migrations\\1712520000000-FeedImport.ts", "source_location": "L1"}, {"id": "1712520000000_feedimport_feedimport1712520000000", "label": "FeedImport1712520000000", "file_type": "code", "source_file": "apps\\api\\src\\database\\migrations\\1712520000000-FeedImport.ts", "source_location": "L3"}, {"id": "1712520000000_feedimport_feedimport1712520000000_up", "label": ".up()", "file_type": "code", "source_file": "apps\\api\\src\\database\\migrations\\1712520000000-FeedImport.ts", "source_location": "L6"}, {"id": "1712520000000_feedimport_feedimport1712520000000_down", "label": ".down()", "file_type": "code", "source_file": "apps\\api\\src\\database\\migrations\\1712520000000-FeedImport.ts", "source_location": "L51"}], "edges": [{"source": "1712520000000_feedimport", "target": "typeorm", "relation": "imports_from", "confidence": "EXTRACTED", "source_file": "apps\\api\\src\\database\\migrations\\1712520000000-FeedImport.ts", "source_location": "L1", "weight": 1.0}, {"source": "1712520000000_feedimport", "target": "1712520000000_feedimport_feedimport1712520000000", "relation": "contains", "confidence": "EXTRACTED", "source_file": "apps\\api\\src\\database\\migrations\\1712520000000-FeedImport.ts", "source_location": "L3", "weight": 1.0}, {"source": "1712520000000_feedimport_feedimport1712520000000", "target": "1712520000000_feedimport_feedimport1712520000000_up", "relation": "method", "confidence": "EXTRACTED", "source_file": "apps\\api\\src\\database\\migrations\\1712520000000-FeedImport.ts", "source_location": "L6", "weight": 1.0}, {"source": "1712520000000_feedimport_feedimport1712520000000", "target": "1712520000000_feedimport_feedimport1712520000000_down", "relation": "method", "confidence": "EXTRACTED", "source_file": "apps\\api\\src\\database\\migrations\\1712520000000-FeedImport.ts", "source_location": "L51", "weight": 1.0}]}